cubit_mesh_export.py
sample_script/cubit_mesh_export_2d_geo_lukas_format.py
sample_script/cubit_mesh_export_3d_cdb.py
sample_script/cubit_mesh_export_3d_freefem_mesh.py
sample_script/cubit_mesh_export_3d_gmesh_v4.py
coreform_cubit_mesh_export-1.1.0.dist-info/METADATA
coreform_cubit_mesh_export-1.1.0.dist-info/WHEEL
coreform_cubit_mesh_export-1.1.0.dist-info/top_level.txt
coreform_cubit_mesh_export-1.1.0.dist-info/RECORD
